inteliallm/__init__.py
inteliallm/client.py
inteliallm-0.2.2.dist-info/METADATA
inteliallm-0.2.2.dist-info/WHEEL
inteliallm-0.2.2.dist-info/RECORD
