Metadata-Version: 2.3
Name: inteliallm
Version: 0.2.2
Summary: Acesso ao LiteLLM da Intelia para consultas e geração de respostas.
Author: rodney silva
Author-email: ro.rss.129@gmail.com
Requires-Python: >=3.11
Classifier: Programming Language :: Python :: 3
Classifier: Programming Language :: Python :: 3.11
Classifier: Programming Language :: Python :: 3.12
Classifier: Programming Language :: Python :: 3.13
Requires-Dist: dirtyjson (>=1.0.8,<2.0.0)
Requires-Dist: openai (>=1.91.0,<2.0.0)
Requires-Dist: python-slugify (>=8.0.4,<9.0.0)
Requires-Dist: redis (>=6.2.0,<7.0.0)
Requires-Dist: requests (>=2.32.4,<3.0.0)
